cnHeat/__init__.py
cnheat-0.1.10.dist-info/METADATA
cnheat-0.1.10.dist-info/WHEEL
cnheat-0.1.10.dist-info/top_level.txt
cnheat-0.1.10.dist-info/RECORD
